README.md
pyproject.toml
src/mmisp/api_client/__init__.py
src/mmisp/api_client/client.py
src/mmisp/api_client/errors.py
src/mmisp/api_client/py.typed
src/mmisp/api_client/types.py
src/mmisp/api_client/api/__init__.py
src/mmisp/api_client/api/attributes/__init__.py
src/mmisp/api_client/api/attributes/add_attribute_attributes_event_id_post.py
src/mmisp/api_client/api/attributes/add_attribute_depr_attributes_add_event_id_post.py
src/mmisp/api_client/api/attributes/add_tag_to_attribute_attributes_add_tag_attribute_id_tag_id_local_local_post.py
src/mmisp/api_client/api/attributes/delete_attribute_attributes_attribute_id_delete.py
src/mmisp/api_client/api/attributes/delete_attribute_depr_attributes_delete_attribute_id_delete.py
src/mmisp/api_client/api/attributes/get_attribute_details_attributes_attribute_id_get.py
src/mmisp/api_client/api/attributes/get_attribute_details_depr_attributes_view_attribute_id_get.py
src/mmisp/api_client/api/attributes/get_attributes_attributes_get.py
src/mmisp/api_client/api/attributes/get_attributes_category_statistics_attributes_attribute_statistics_category_percentage_get.py
src/mmisp/api_client/api/attributes/get_attributes_describe_types_attributes_describe_types_get.py
src/mmisp/api_client/api/attributes/get_attributes_type_statistics_attributes_attribute_statistics_type_percentage_get.py
src/mmisp/api_client/api/attributes/remove_tag_from_attribute_attributes_remove_tag_attribute_id_tag_id_post.py
src/mmisp/api_client/api/attributes/rest_search_attributes_attributes_rest_search_post.py
src/mmisp/api_client/api/attributes/restore_attribute_attributes_restore_attribute_id_post.py
src/mmisp/api_client/api/attributes/update_attribute_attributes_attribute_id_put.py
src/mmisp/api_client/api/attributes/update_attribute_depr_attributes_edit_attribute_id_put.py
src/mmisp/api_client/api/auth_keys/__init__.py
src/mmisp/api_client/api/auth_keys/auth_keys_add_user_auth_keys_user_id_post.py
src/mmisp_api_client.egg-info/PKG-INFO
src/mmisp_api_client.egg-info/SOURCES.txt
src/mmisp_api_client.egg-info/dependency_links.txt
src/mmisp_api_client.egg-info/requires.txt
src/mmisp_api_client.egg-info/top_level.txt