Metadata-Version: 2.4
Name: mmisp-api-client
Version: 0.8.0
Summary: A client library for accessing Modern MISP API
Requires-Python: >=3.11.0
Requires-Dist: httpx<0.29.0,>=0.20.0
Requires-Dist: attrs>=22.2.0
Requires-Dist: python-dateutil~=2.8.0
